pycangjie/__init__.py
pycangjie/core.py
pycangjie/pkg_data.json
pycangjie-0.0.10.dist-info/LICENSE
pycangjie-0.0.10.dist-info/METADATA
pycangjie-0.0.10.dist-info/WHEEL
pycangjie-0.0.10.dist-info/top_level.txt
pycangjie-0.0.10.dist-info/RECORD
