Metadata-Version: 2.1
Name: pycangjie
Version: 0.0.10
Summary: CangJie 倉頡 dictionary API.
Home-page: https://github.com/foxe6/pycangjie
Author: f̣ộx̣ệ6
Author-email: foxe6@protonmail.com
License: AGPL-3.0
Keywords: quickcopy quick copy
Platform: UNKNOWN
Classifier: Programming Language :: Python :: 3.7
Classifier: Topic :: Utilities
Classifier: Natural Language :: English
Classifier: Intended Audience :: Developers
Classifier: License :: OSI Approved :: GNU Affero General Public License v3
Classifier: Operating System :: Microsoft :: Windows :: Windows 10
Requires-Python: >=3
Requires-Dist: threadwrapper (>=0.0.1)
Requires-Dist: lxml (>=0.0.1)
